{"_invocation_id": "c52ad986-c232-46a1-839b-6bfbb1768665", "linked": {"0": {"name": "source.sales_lab.raw.CUSTOMERS", "type": "source", "succ": [20, 24]}, "1": {"name": "source.sales_lab.raw.EMPLOYEES", "type": "source", "succ": [21]}, "2": {"name": "source.sales_lab.raw.OFFICES", "type": "source"}, "3": {"name": "source.sales_lab.raw.ORDERS", "type": "source", "succ": [20, 22]}, "4": {"name": "source.sales_lab.raw.ORDERDETAILS", "type": "source", "succ": [20]}, "5": {"name": "source.sales_lab.raw.PRODUCTS", "type": "source", "succ": [23]}, "6": {"name": "source.sales_lab.raw.PRODUCTLINES", "type": "source"}, "7": {"name": "model.sales_lab.my_first_dbt_model", "type": "model", "succ": [8, 9, 10]}, "8": {"name": "model.sales_lab.my_second_dbt_model", "type": "model", "succ": [11, 12]}, "9": {"name": "test.sales_lab.unique_my_first_dbt_model_id.16e066b321", "type": "test"}, "10": {"name": "test.sales_lab.not_null_my_first_dbt_model_id.5fb22c2710", "type": "test"}, "11": {"name": "test.sales_lab.unique_my_second_dbt_model_id.57a0f8c493", "type": "test"}, "12": {"name": "test.sales_lab.not_null_my_second_dbt_model_id.151b76d778", "type": "test"}, "13": {"name": "model.sales_lab.stg_orders", "type": "model"}, "14": {"name": "model.sales_lab.stg_orderdetails", "type": "model"}, "15": {"name": "model.sales_lab.stg_productlines", "type": "model"}, "16": {"name": "model.sales_lab.stg_offices", "type": "model"}, "17": {"name": "model.sales_lab.stg_employees", "type": "model"}, "18": {"name": "model.sales_lab.stg_customers", "type": "model"}, "19": {"name": "model.sales_lab.stg_products", "type": "model"}, "20": {"name": "model.sales_lab.fact_sales", "type": "model"}, "21": {"name": "model.sales_lab.dim_employees", "type": "model"}, "22": {"name": "model.sales_lab.dim_date", "type": "model"}, "23": {"name": "model.sales_lab.dim_products", "type": "model"}, "24": {"name": "model.sales_lab.dim_customers", "type": "model"}}}